{
"lettre1" : "ف ",
"lettre2" : "ب ",
"lettre3" : " ",
"lettre4" : " لا ",
"lettre5" : "ب  ",
"lettre6" : "  ",
"lettre7" : "غ",
"lettre8" : "ت",
"lettre9" : " ",
"lettre10" : " ى  ",
"lettre11" : "ت ",
"lettre12" : " ",
"lettre13" : " ق ",
"lettre14" : "ب  ",
"lettre15" : " ",
"lettre16" : "ر",
"lettre17" : " ب ",


"lettre18" : "ر ",
"lettre19" : "ت  ",
"lettre20" : " ",
"lettre21" : "ة ",
"lettre22" : "ت  ",
"lettre23" : " ",
"lettre24" : "ث ",
"lettre25" : "ي  ",
"lettre26" : " ",
"lettre27" : " ؤ ",
"lettre28" : "ي  ",
"lettre29" : " ",
"lettre30" : " ه ",
"lettre31" : "ن  ",
"lettre32" : " ",
"lettre33" : " و ",
"lettre34" : "ن ",



"lettre35" : "ص",
"lettre36" : "س",
"lettre37" : "  ",
"lettre38" : "ء",
"lettre39" : "س",
"lettre40" : " ",
"lettre41" : "خ",
"lettre42" : "م",
"lettre43" : " ",
"lettre44" : "ز",
"lettre45" : "م",
"lettre46" : " ",
"lettre47" : "ئ ",
"lettre48" : "ش",

"lettre49" : "ح",
"lettre50" : "",
"lettre51" : " ",
"lettre52" : " ظ ",
"lettre53" : "ت",
"lettre54" : " ",
"lettre55" : "ر",
"lettre56" : "ب ",
"lettre57" : "لا ",
"lettre58" : "ب ",
"lettre59" : " ",
"lettre60" : " ت ",
"lettre61" : "  ى  ",
"lettre62" : " ة  ",
"lettre63" : "ت ",


"lettre64" : " ؤ",
"lettre65" : " ي ",
"lettre66" : " و ",
"lettre67" : "  ن ",
"lettre68 : " ",
"lettre69" : " ء",
"lettre70" : " س",
"lettre71" : " ز",
"lettre72" : " م ",
"lettre73" : " ",
"lettre74" : " ئ",
"lettre75" : " ش",
"lettre76" : " ظ",
"lettre77" : " ك"
}